xai_grok_sdk/__init__.py
xai_grok_sdk/models.py
xai_grok_sdk/xai.py
xai_grok_sdk-0.0.12.dist-info/LICENSE
xai_grok_sdk-0.0.12.dist-info/METADATA
xai_grok_sdk-0.0.12.dist-info/WHEEL
xai_grok_sdk-0.0.12.dist-info/top_level.txt
xai_grok_sdk-0.0.12.dist-info/RECORD
